LICENSE
MANIFEST.in
README.rst
requirements.txt
setup.cfg
setup.py
ckanext/__init__.py
ckanext/cepsadata_theme/__init__.py
ckanext/cepsadata_theme/plugin.py
ckanext/cepsadata_theme/fanstatic/cepsadata_theme.css
ckanext/cepsadata_theme/templates/base.html
ckanext/cepsadata_theme/templates/home/index.html
ckanext/cepsadata_theme/templates/home/layout2.html
ckanext/cepsadata_theme/templates/home/snippets/about_text.html
ckanext/cepsadata_theme/templates/home/snippets/featured_group.html
ckanext/cepsadata_theme/templates/home/snippets/featured_organization.html
ckanext/cepsadata_theme/templates/home/snippets/promoted.html
ckanext/cepsadata_theme/templates/home/snippets/search.html
ckanext/cepsadata_theme/templates/home/snippets/stats.html
ckanext/cepsadata_theme/tests/__init__.py
ckanext/cepsadata_theme/tests/test_plugin.py
ckanext_cepsadata_theme.egg-info/PKG-INFO
ckanext_cepsadata_theme.egg-info/SOURCES.txt
ckanext_cepsadata_theme.egg-info/dependency_links.txt
ckanext_cepsadata_theme.egg-info/entry_points.txt
ckanext_cepsadata_theme.egg-info/namespace_packages.txt
ckanext_cepsadata_theme.egg-info/top_level.txt