Metadata-Version: 1.1
Name: ckanext-cepsadata-theme
Version: 0.0.1
Summary: Theme para cepsadata
Home-page: https://github.com/backstageel/ckanext-cepsadata_theme
Author: Elisio Leonardo
Author-email: elisio.leonardo@gmail.com
License: AGPL
Keywords: CKAN Cepsadata
Platform: UNKNOWN
Classifier: Development Status :: 4 - Beta
Classifier: License :: OSI Approved :: GNU Affero General Public License v3 or later (AGPLv3+)
Classifier: Programming Language :: Python :: 2.7
